utencilos/__init__.py
utencilos/general.py
utencilos-0.0.3.dist-info/LICENSE
utencilos-0.0.3.dist-info/METADATA
utencilos-0.0.3.dist-info/WHEEL
utencilos-0.0.3.dist-info/top_level.txt
utencilos-0.0.3.dist-info/RECORD
