Metadata-Version: 2.1
Name: utencilos
Version: 0.0.3
Summary: A collection of useful code for working with data.
Author-email: Anthony Castro-Yoskovich <author@example.com>
Project-URL: Homepage, https://github.com/pypa/sampleproject
Project-URL: Bug Tracker, https://github.com/pypa/sampleproject/issues
Classifier: Programming Language :: Python :: 3
Classifier: License :: OSI Approved :: MIT License
Classifier: Operating System :: OS Independent
Requires-Python: >=3.7
License-File: LICENSE
Requires-Dist: pandas (==1.5.3)
